rbcommenttype/__init__.py
rbcommenttype/admin_urls.py
rbcommenttype/extension.py
rbcommenttype/forms.py
rbcommenttype/static/css/comment-type-configure.min.38bcf3759e51.css
rbcommenttype/static/css/comment-type-configure.min.css
rbcommenttype/static/css/configure.3b6369de217c.less
rbcommenttype/static/css/configure.css
rbcommenttype/static/css/configure.css.map
rbcommenttype/static/css/configure.less
rbcommenttype/static/js/comment-type-configure.min.a831e8cde021.js
rbcommenttype/static/js/comment-type-configure.min.js
rbcommenttype/static/js/comment-type.min.21b102f5917a.js
rbcommenttype/static/js/comment-type.min.js
rbcommenttype/static/js/commentType.cd400ac40667.js
rbcommenttype/static/js/commentType.js
rbcommenttype/static/js/configure.16c01e0012bd.js
rbcommenttype/static/js/configure.js
rbcommenttype/templates/rbcommenttype-types.html
rbcommenttype-2.0.dist-info/METADATA
rbcommenttype-2.0.dist-info/WHEEL
rbcommenttype-2.0.dist-info/entry_points.txt
rbcommenttype-2.0.dist-info/top_level.txt
rbcommenttype-2.0.dist-info/RECORD
